[
    {
        "site": "bluesky",
        "url": "https://bsky.app/profile/itsmeat.neocities.org",
        "handle":"friendmeat.org"
    },
    {
        "site": "mastodon",
        "url": "https://meow.social/@friendmeat",
        "handle":"@friendmeat"
    },
    {
        "site": "tumblr",
        "url": "https://friendmeat.tumblr.com/",
        "handle":"@friendmeat"
    },
    {
        "site": "twitter",
        "url": "https://twitter.com/friend_meat",
        "handle":"@friend_meat"
    }
]